opsys_logger/__init__.py
opsys_logger/print_formatter.py
opsys_logger/print_formatter_abstract.py
opsys_logger-0.0.2.dist-info/LICENSE
opsys_logger-0.0.2.dist-info/METADATA
opsys_logger-0.0.2.dist-info/WHEEL
opsys_logger-0.0.2.dist-info/top_level.txt
opsys_logger-0.0.2.dist-info/RECORD
